Workbook

Sheet Instructions
A1: Commercial Sales Analysis | Dubai Retail Chain, 2025
A3: Sheets in this workbook
A4: Sales: 4,200 order lines (Jan-Dec 2025) across 5 stores. Raw data, one row per order line.
A5: Products: 36 products with name, category, sub-category and unit cost (AED). Used as the lookup table.
A7: Cells to fill in
A8: Yellow header cells on the Sales sheet (columns H to N) are empty. You add formulas there, step by step.
A9: Example (first data row, ORD50478): Product_Name = Women's Summer Dress, Category = Fashion, Unit_Cost_AED = 120,
A10: Revenue_AED = 194.65, Cost_AED = 120, Profit_AED = 74.65, Month = Jan
A12: Column definitions
A13: Revenue_AED = Quantity x Unit_Price_AED x (1 - Discount_Pct)
A14: Cost_AED = Quantity x Unit_Cost_AED
A15: Profit_AED = Revenue_AED - Cost_AED
A17: Data note: simulated data for a fictional Dubai retail chain, created for a portfolio project.

Sheet Sales
A1: Order_ID | B1: Order_Date | C1: Store | D1: Product_ID | E1: Quantity | F1: Unit_Price_AED | G1: Discount_Pct | H1: Product_Name | I1: Category | J1: Unit_Cost_AED | K1: Revenue_AED | L1: Cost_AED | M1: Profit_AED | N1: Month
A2: ORD50478 | B2: 45658 | C2: Mall of the Emirates | D2: P308 | E2: 1 | F2: 229 | G2: 0.15 | H2: =INDEX(Products!$B$2:$B$37, MATCH(D2, Products!$A$2:$A$37, 0)) -> Women's Summer Dress | I2: =INDEX(Products!$C$2:$C$37, MATCH(D2, Products!$A$2:$A$37, 0)) -> Fashion | J2: =INDEX(Products!$E$2:$E$37, MATCH(D2, Products!$A$2:$A$37, 0)) -> 120 | K2: =E2*F2*(1-G2) -> 194.65 | L2: =E2*J2 -> 120 | M2: =K2-L2 -> 74.65 | N2: =TEXT(B2,"mmm") -> Jan
A3: ORD50602 | B3: 45658 | C3: City Centre Deira | D3: P308 | E3: 2 | F3: 229 | G3: 0.05 | H3: =INDEX(Products!$B$2:$B$37, MATCH(D3, Products!$A$2:$A$37, 0)) -> Women's Summer Dress | I3: =INDEX(Products!$C$2:$C$37, MATCH(D3, Products!$A$2:$A$37, 0)) -> Fashion | J3: =INDEX(Products!$E$2:$E$37, MATCH(D3, Products!$A$2:$A$37, 0)) -> 120 | K3: =E3*F3*(1-G3) -> 435.1 | L3: =E3*J3 -> 240 | M3: =K3-L3 -> 195.1 | N3: =TEXT(B3,"mmm") -> Jan
A4: ORD51438 | B4: 45658 | C4: City Centre Deira | D4: P104 | E4: 1 | F4: 199 | G4: 0.1 | H4: =INDEX(Products!$B$2:$B$37, MATCH(D4, Products!$A$2:$A$37, 0)) -> Fitness Band Lite | I4: =INDEX(Products!$C$2:$C$37, MATCH(D4, Products!$A$2:$A$37, 0)) -> Electronics | J4: =INDEX(Products!$E$2:$E$37, MATCH(D4, Products!$A$2:$A$37, 0)) -> 175 | K4: =E4*F4*(1-G4) -> 179.1 | L4: =E4*J4 -> 175 | M4: =K4-L4 -> 4.1 | N4: =TEXT(B4,"mmm") -> Jan
A5: ORD52069 | B5: 45658 | C5: City Centre Deira | D5: P301 | E5: 2 | F5: 179 | G5: 0 | H5: =INDEX(Products!$B$2:$B$37, MATCH(D5, Products!$A$2:$A$37, 0)) -> Men's Linen Shirt | I5: =INDEX(Products!$C$2:$C$37, MATCH(D5, Products!$A$2:$A$37, 0)) -> Fashion | J5: =INDEX(Products!$E$2:$E$37, MATCH(D5, Products!$A$2:$A$37, 0)) -> 70 | K5: =E5*F5*(1-G5) -> 358 | L5: =E5*J5 -> 140 | M5: =K5-L5 -> 218 | N5: =TEXT(B5,"mmm") -> Jan
A6: ORD52175 | B6: 45658 | C6: City Centre Deira | D6: P306 | E6: 1 | F6: 249 | G6: 0 | H6: =INDEX(Products!$B$2:$B$37, MATCH(D6, Products!$A$2:$A$37, 0)) -> Sunglasses Polarised | I6: =INDEX(Products!$C$2:$C$37, MATCH(D6, Products!$A$2:$A$37, 0)) -> Fashion | J6: =INDEX(Products!$E$2:$E$37, MATCH(D6, Products!$A$2:$A$37, 0)) -> 95 | K6: =E6*F6*(1-G6) -> 249 | L6: =E6*J6 -> 95 | M6: =K6-L6 -> 154 | N6: =TEXT(B6,"mmm") -> Jan
A7: ORD52186 | B7: 45658 | C7: City Centre Deira | D7: P406 | E7: 1 | F7: 199 | G7: 0 | H7: =INDEX(Products!$B$2:$B$37, MATCH(D7, Products!$A$2:$A$37, 0)) -> Bakhoor Gift Set | I7: =INDEX(Products!$C$2:$C$37, MATCH(D7, Products!$A$2:$A$37, 0)) -> Beauty | J7: =INDEX(Products!$E$2:$E$37, MATCH(D7, Products!$A$2:$A$37, 0)) -> 90 | K7: =E7*F7*(1-G7) -> 199 | L7: =E7*J7 -> 90 | M7: =K7-L7 -> 109 | N7: =TEXT(B7,"mmm") -> Jan
A8: ORD53044 | B8: 45658 | C8: Online | D8: P101 | E8: 1 | F8: 399 | G8: 0.1 | H8: =INDEX(Products!$B$2:$B$37, MATCH(D8, Products!$A$2:$A$37, 0)) -> Wireless Earbuds Pro | I8: =INDEX(Products!$C$2:$C$37, MATCH(D8, Products!$A$2:$A$37, 0)) -> Electronics | J8: =INDEX(Products!$E$2:$E$37, MATCH(D8, Products!$A$2:$A$37, 0)) -> 230 | K8: =E8*F8*(1-G8) -> 359.1 | L8: =E8*J8 -> 230 | M8: =K8-L8 -> 129.1 | N8: =TEXT(B8,"mmm") -> Jan
A9: ORD53052 | B9: 45658 | C9: Dubai Mall | D9: P306 | E9: 1 | F9: 249 | G9: 0 | H9: =INDEX(Products!$B$2:$B$37, MATCH(D9, Products!$A$2:$A$37, 0)) -> Sunglasses Polarised | I9: =INDEX(Products!$C$2:$C$37, MATCH(D9, Products!$A$2:$A$37, 0)) -> Fashion | J9: =INDEX(Products!$E$2:$E$37, MATCH(D9, Products!$A$2:$A$37, 0)) -> 95 | K9: =E9*F9*(1-G9) -> 249 | L9: =E9*J9 -> 95 | M9: =K9-L9 -> 154 | N9: =TEXT(B9,"mmm") -> Jan
A10: ORD53339 | B10: 45658 | C10: City Centre Deira | D10: P404 | E10: 1 | F10: 189 | G10: 0.1 | H10: =INDEX(Products!$B$2:$B$37, MATCH(D10, Products!$A$2:$A$37, 0)) -> Makeup Palette | I10: =INDEX(Products!$C$2:$C$37, MATCH(D10, Products!$A$2:$A$37, 0)) -> Beauty | J10: =INDEX(Products!$E$2:$E$37, MATCH(D10, Products!$A$2:$A$37, 0)) -> 85 | K10: =E10*F10*(1-G10) -> 170.1 | L10: =E10*J10 -> 85 | M10: =K10-L10 -> 85.1 | N10: =TEXT(B10,"mmm") -> Jan
A11: ORD53546 | B11: 45658 | C11: Ibn Battuta Mall | D11: P303 | E11: 2 | F11: 149 | G11: 0.3 | H11: =INDEX(Products!$B$2:$B$37, MATCH(D11, Products!$A$2:$A$37, 0)) -> Kids' Sneakers | I11: =INDEX(Products!$C$2:$C$37, MATCH(D11, Products!$A$2:$A$37, 0)) -> Fashion | J11: =INDEX(Products!$E$2:$E$37, MATCH(D11, Products!$A$2:$A$37, 0)) -> 80 | K11: =E11*F11*(1-G11) -> 208.6 | L11: =E11*J11 -> 160 | M11: =K11-L11 -> 48.6 | N11: =TEXT(B11,"mmm") -> Jan
A12: ORD54087 | B12: 45658 | C12: Dubai Mall | D12: P308 | E12: 2 | F12: 229 | G12: 0.05 | H12: =INDEX(Products!$B$2:$B$37, MATCH(D12, Products!$A$2:$A$37, 0)) -> Women's Summer Dress | I12: =INDEX(Products!$C$2:$C$37, MATCH(D12, Products!$A$2:$A$37, 0)) -> Fashion | J12: =INDEX(Products!$E$2:$E$37, MATCH(D12, Products!$A$2:$A$37, 0)) -> 120 | K12: =E12*F12*(1-G12) -> 435.1 | L12: =E12*J12 -> 240 | M12: =K12-L12 -> 195.1 | N12: =TEXT(B12,"mmm") -> Jan
A13: ORD54094 | B13: 45658 | C13: Online | D13: P403 | E13: 1 | F13: 299 | G13: 0.15 | H13: =INDEX(Products!$B$2:$B$37, MATCH(D13, Products!$A$2:$A$37, 0)) -> Hair Dryer Ionic | I13: =INDEX(Products!$C$2:$C$37, MATCH(D13, Products!$A$2:$A$37, 0)) -> Beauty | J13: =INDEX(Products!$E$2:$E$37, MATCH(D13, Products!$A$2:$A$37, 0)) -> 240 | K13: =E13*F13*(1-G13) -> 254.15 | L13: =E13*J13 -> 240 | M13: =K13-L13 -> 14.15 | N13: =TEXT(B13,"mmm") -> Jan
... A4201: ORD53930 | B4201: 46022 | C4201: Mall of the Emirates | D4201: P402 | E4201: 1 | F4201: 149 | G4201: 0.1 | H4201: =INDEX(Products!$B$2:$B$37, MATCH(D4201, Products!$A$2:$A$37, 0)) -> Vitamin C Serum | I4201: =INDEX(Products!$C$2:$C$37, MATCH(D4201, Products!$A$2:$A$37, 0)) -> Beauty | J4201: =INDEX(Products!$E$2:$E$37, MATCH(D4201, Products!$A$2:$A$37, 0)) -> 55 | K4201: =E4201*F4201*(1-G4201) -> 134.1 | L4201: =E4201*J4201 -> 55 | M4201: =K4201-L4201 -> 79.1 | N4201: =TEXT(B4201,"mmm") -> Dec

Sheet Products
A1: Product_ID | B1: Product_Name | C1: Category | D1: Sub_Category | E1: Unit_Cost_AED
A2: P101 | B2: Wireless Earbuds Pro | C2: Electronics | D2: Audio | E2: 230
A3: P102 | B3: Bluetooth Speaker Mini | C3: Electronics | D3: Audio | E3: 150
A4: P103 | B4: Smart Watch Series 5 | C4: Electronics | D4: Wearables | E4: 820
A5: P104 | B5: Fitness Band Lite | C5: Electronics | D5: Wearables | E5: 175
A6: P105 | B6: 4K Action Camera | C6: Electronics | D6: Cameras | E6: 610
A7: P106 | B7: Power Bank 20000mAh | C7: Electronics | D7: Accessories | E7: 70
A8: P107 | B8: USB-C Fast Charger | C8: Electronics | D8: Accessories | E8: 35
A9: P108 | B9: Gaming Headset X | C9: Electronics | D9: Audio | E9: 300
A10: P201 | B10: Air Fryer 5L | C10: Home & Kitchen | D10: Appliances | E10: 290
A11: P202 | B11: Espresso Machine | C11: Home & Kitchen | D11: Appliances | E11: 1050
A12: P203 | B12: Non-stick Cookware Set | C12: Home & Kitchen | D12: Cookware | E12: 170
A13: P204 | B13: Robot Vacuum S3 | C13: Home & Kitchen | D13: Appliances | E13: 1080
... A37: P506 | B37: Swim Goggles | C37: Sports | D37: Swimming | E37: 25

Sheet Summary
A1: Category | B1: Revenue (AED) | C1: Profit (AED) | D1: Margin %
A2: Fashion | B2: =SUMIFS(Sales!$K$2:$K$4201,Sales!$I$2:$I$4201,A2) -> 542663.95 | C2: =SUMIFS(Sales!$M$2:$M$4201, Sales!$I$2:$I$4201, A2) -> 247053.95 | D2: =C2/B2 -> 0.4552614
A3: Electronics | B3: =SUMIFS(Sales!$K$2:$K$4201,Sales!$I$2:$I$4201,A3) -> 540405.5 | C3: =SUMIFS(Sales!$M$2:$M$4201, Sales!$I$2:$I$4201, A3) -> 160285.5 | D3: =C3/B3 -> 0.29660227
A4: Home & Kitchen | B4: =SUMIFS(Sales!$K$2:$K$4201,Sales!$I$2:$I$4201,A4) -> 438429.45 | C4: =SUMIFS(Sales!$M$2:$M$4201, Sales!$I$2:$I$4201, A4) -> 137104.45 | D4: =C4/B4 -> 0.31271725
A5: Beauty | B5: =SUMIFS(Sales!$K$2:$K$4201,Sales!$I$2:$I$4201,A5) -> 250150.25 | C5: =SUMIFS(Sales!$M$2:$M$4201, Sales!$I$2:$I$4201, A5) -> 106585.25 | D5: =C5/B5 -> 0.42608492
A6: Sports | B6: =SUMIFS(Sales!$K$2:$K$4201,Sales!$I$2:$I$4201,A6) -> 221143.1 | C6: =SUMIFS(Sales!$M$2:$M$4201, Sales!$I$2:$I$4201, A6) -> 23743.1 | D6: =C6/B6 -> 0.10736532
A7: Total | B7: =SUM(B2:B6) -> 1992792.3 | C7: =SUM(C2:C6) -> 674772.25 | D7: =C7/B7 -> 0.33860642
A9: Store | B9: Revenue (AED) | C9: Profit (AED) | D9: Margin %
A10: Dubai Mall | B10: =SUMIFS(Sales!$K$2:$K$4201, Sales!$C$2:$C$4201, A10) -> 518646.95 | C10: =SUMIFS(Sales!$M$2:$M$4201, Sales!$C$2:$C$4201, A10) -> 175421.95 | D10: =C10/B10 -> 0.33822998
A11: Online | B11: =SUMIFS(Sales!$K$2:$K$4201, Sales!$C$2:$C$4201, A11) -> 497274.95 | C11: =SUMIFS(Sales!$M$2:$M$4201, Sales!$C$2:$C$4201, A11) -> 158104.95 | D11: =C11/B11 -> 0.31794272
A12: Mall of the Emirates | B12: =SUMIFS(Sales!$K$2:$K$4201, Sales!$C$2:$C$4201, A12) -> 443840.1 | C12: =SUMIFS(Sales!$M$2:$M$4201, Sales!$C$2:$C$4201, A12) -> 154500.1 | D12: =C12/B12 -> 0.34809856
A13: City Centre Deira | B13: =SUMIFS(Sales!$K$2:$K$4201, Sales!$C$2:$C$4201, A13) -> 273697.75 | C13: =SUMIFS(Sales!$M$2:$M$4201, Sales!$C$2:$C$4201, A13) -> 94292.75 | D13: =C13/B13 -> 0.34451416
A14: Ibn Battuta Mall | B14: =SUMIFS(Sales!$K$2:$K$4201, Sales!$C$2:$C$4201, A14) -> 259332.5 | C14: =SUMIFS(Sales!$M$2:$M$4201, Sales!$C$2:$C$4201, A14) -> 92452.5 | D14: =C14/B14 -> 0.35650179

Sheet Discount Impact
A3: Row Labels | B3: Sum of Margin
A4: 0 | B4: 0.45768558
A5: 0.05 | B5: 0.44192537
A6: 0.1 | B6: 0.33288395
A7: 0.15 | B7: 0.23478328
A8: 0.2 | B8: 0.20221348
A9: 0.25 | B9: -0.15113831
A10: 0.3 | B10: 0.21126904
A11: Grand Total | B11: 0.33860642

Sheet Monthly
A3: Row Labels | B3: Sum of Revenue_AED | C3: Sum of Profit_AED
A4: Jan | B4: 186525.75 | C4: 64575.75
A5: Feb | B5: 156992.35 | C5: 55377.35
A6: Mar | B6: 163707.75 | C6: 55912.75
A7: Apr | B7: 199434.15 | C7: 58009.15
A8: May | B8: 186293.3 | C8: 63898.3
A9: Jun | B9: 154533.6 | C9: 55118.6
A10: Jul | B10: 162833.85 | C10: 60618.85
A11: Aug | B11: 160798.6 | C11: 56633.6
A12: Sep | B12: 158335.5 | C12: 55445.5
A13: Oct | B13: 173814.8 | C13: 57314.8
A14: Nov | B14: 134524.8 | C14: 43534.8
A15: Dec | B15: 154997.8 | C15: 48332.8
A16: Grand Total | B16: 1992792.2 | C16: 674772.25

Sheet Product Profit
A3: Row Labels | B3: Sum of Revenue_AED | C3: Sum of Profit_AED | D3: Sum of Margin
A4: Robot Vacuum S3 | B4: 63666.9 | C4: -6533.1 | D4: -0.10261376
A5: Treadmill Compact | B5: 83841.45 | C5: -6458.55 | D5: -0.0770329
A6: Adjustable Dumbbells | B6: 66077.3 | C6: -3922.7 | D6: -0.059365319
A7: Fitness Band Lite | B7: 42725.3 | C7: -3299.7 | D7: -0.077230587
A8: Hair Dryer Ionic | B8: 46150.65 | C8: 790.65 | D8: 0.017131936
A9: Swim Goggles | B9: 8521.5 | C9: 5171.5 | D9: 0.60687672
A10: Football Size 5 | B10: 11682 | C10: 5832 | D10: 0.49922958
A11: Yoga Mat Premium | B11: 17976.15 | C11: 8916.15 | D11: 0.49599887
A12: Sunscreen SPF50 | B12: 19179.5 | C12: 9819.5 | D12: 0.51197894
A13: Electric Kettle | B13: 22987.8 | C13: 11347.8 | D13: 0.49364445
A14: USB-C Fast Charger | B14: 22472.5 | C14: 12777.5 | D14: 0.56858382
A15: Cycling Helmet | B15: 33044.7 | C15: 14204.7 | D15: 0.42986319
... A40: Grand Total | B40: 1992792.2 | C40: 674772.25 | D40: 0.33860642

Sheet Dashboard
B2: Commercial Sales Dashboard | Dubai Retail 2025
B4: Total Revenue (AED) | D4: Total Profit (AED) | F4: Profit Margin | H4: Order Lines
B5: =Summary!B7 -> 1992792.3 | D5: =Summary!C7 -> 674772.25 | F5: =Summary!D7 -> 0.33860642 | H5: =COUNTA(Sales!A2:A4201) -> 4200
F25: Loss-Making Products (Bottom 5)
F26: Product | H26: Profit (AED)
F27: ='Product Profit'!A4 -> Robot Vacuum S3 | H27: =GETPIVOTDATA("Sum of Profit_AED",'Product Profit'!$A$3,"Product_Name","Robot Vacuum S3") -> -6533.1
F28: ='Product Profit'!A5 -> Treadmill Compact | H28: =GETPIVOTDATA("Sum of Profit_AED",'Product Profit'!$A$3,"Product_Name","Treadmill Compact") -> -6458.55
F29: ='Product Profit'!A6 -> Adjustable Dumbbells | H29: =GETPIVOTDATA("Sum of Profit_AED",'Product Profit'!$A$3,"Product_Name","Adjustable Dumbbells") -> -3922.7
F30: ='Product Profit'!A7 -> Fitness Band Lite | H30: =GETPIVOTDATA("Sum of Profit_AED",'Product Profit'!$A$3,"Product_Name","Fitness Band Lite") -> -3299.7
F31: ='Product Profit'!A8 -> Hair Dryer Ionic | H31: =GETPIVOTDATA("Sum of Profit_AED",'Product Profit'!$A$3,"Product_Name","Hair Dryer Ionic") -> 790.65
